package_ephraim/__init__.py
package_ephraim/api_dealer.py
package_ephraim-0.1.dist-info/METADATA
package_ephraim-0.1.dist-info/WHEEL
package_ephraim-0.1.dist-info/top_level.txt
package_ephraim-0.1.dist-info/RECORD
